voxpopuli/__init__.py
voxpopuli/main.py
voxpopuli/phonemes.py
voxpopuli/voice_install.py
voxpopuli-0.3.9.dist-info/LICENSE
voxpopuli-0.3.9.dist-info/METADATA
voxpopuli-0.3.9.dist-info/WHEEL
voxpopuli-0.3.9.dist-info/top_level.txt
voxpopuli-0.3.9.dist-info/RECORD
