Metadata-Version: 2.1
Name: voxpopuli
Version: 0.3.9
Summary: A wrapper around Espeak and Mbrola, to do simple Text-To-Speech (TTS), with the possibility to tweak the phonemic form.
Home-page: https://github.com/hadware/voxpopuli
Author: Hadware
Author-email: hadwarez@gmail.com
License: MIT
Keywords: tts speech phonemes audio
Classifier: Topic :: Text Processing :: Linguistic
Classifier: Topic :: Multimedia :: Sound/Audio :: Sound Synthesis
Classifier: Topic :: Multimedia :: Sound/Audio :: Speech
Classifier: Development Status :: 3 - Alpha
Classifier: Intended Audience :: Developers
Classifier: Intended Audience :: Science/Research
Classifier: License :: OSI Approved :: MIT License
Classifier: Programming Language :: Python :: 3
Classifier: Programming Language :: Python :: 3.6
Classifier: Programming Language :: Python :: 3.7
Classifier: Programming Language :: Python :: 3.8
Classifier: Programming Language :: Python :: 3.9
Classifier: Programming Language :: Python :: 3.10
License-File: LICENSE
